pydbus-stubs/__init__.pyi
pydbus-stubs/_inspect3.pyi
pydbus-stubs/auto_names.pyi
pydbus-stubs/bus.pyi
pydbus-stubs/bus_names.pyi
pydbus-stubs/exitable.pyi
pydbus-stubs/generic.pyi
pydbus-stubs/identifier.pyi
pydbus-stubs/method_call_context.pyi
pydbus-stubs/proxy.pyi
pydbus-stubs/proxy_method.pyi
pydbus-stubs/proxy_property.pyi
pydbus-stubs/proxy_signal.pyi
pydbus-stubs/publication.pyi
pydbus-stubs/registration.pyi
pydbus-stubs/request_name.pyi
pydbus-stubs/subscription.pyi
pydbus-stubs/timeout.pyi
pydbus_stubs-0.0.3.dist-info/LICENSE.txt
pydbus_stubs-0.0.3.dist-info/METADATA
pydbus_stubs-0.0.3.dist-info/WHEEL
pydbus_stubs-0.0.3.dist-info/RECORD
