Metadata-Version: 2.1
Name: pydbus-stubs
Version: 0.0.3
Summary: Stubs for pydbus.
Home-page: https://github.com/Tatsh/pydbus-stubs
License: MIT
Keywords: dbus,stubs,typing
Author: Andrew Udvare
Author-email: audvare@gmail.com
Requires-Python: >=3.9,<4
Classifier: Development Status :: 5 - Production/Stable
Classifier: Intended Audience :: Developers
Classifier: License :: OSI Approved :: MIT License
Classifier: Programming Language :: Python
Classifier: Programming Language :: Python :: 3
Classifier: Programming Language :: Python :: 3.9
Classifier: Programming Language :: Python :: 3.10
Classifier: Programming Language :: Python :: 3.11
Classifier: Programming Language :: Python :: 3.12
Classifier: Programming Language :: Python :: 3.13
Classifier: Typing :: Stubs Only
Requires-Dist: pygobject-stubs (>=2.12.0,<3.0.0)
Project-URL: Issues, https://github.com/Tatsh/pydbus-stubs/issues
Project-URL: Repository, https://github.com/Tatsh/pydbus-stubs
